.gitignore
CONTRIBUTORS.rst
MANIFEST.in
README.rst
setup.cfg
setup.py
collective/__init__.py
collective.ruleactions.pythonscript.egg-info/PKG-INFO
collective.ruleactions.pythonscript.egg-info/SOURCES.txt
collective.ruleactions.pythonscript.egg-info/dependency_links.txt
collective.ruleactions.pythonscript.egg-info/entry_points.txt
collective.ruleactions.pythonscript.egg-info/namespace_packages.txt
collective.ruleactions.pythonscript.egg-info/not-zip-safe
collective.ruleactions.pythonscript.egg-info/requires.txt
collective.ruleactions.pythonscript.egg-info/top_level.txt
collective/ruleactions/__init__.py
collective/ruleactions/pythonscript/__init__.py
collective/ruleactions/pythonscript/configure.zcml
collective/ruleactions/pythonscript/pythonscript.py
collective/ruleactions/pythonscript/tests.py
docs/HISTORY.rst
docs/INSTALL.rst
docs/LICENSE.GPL
docs/LICENSE.rst