Metadata-Version: 1.1
Name: collective.ruleactions.pythonscript
Version: 0.1
Summary: UNKNOWN
Home-page: https://github.com/collective/collective.ruleactions.pythonscript
Author: Florian Schulze
Author-email: florian.schulze@gmx.net
License: GPL
Platform: UNKNOWN
Classifier: Framework :: Plone
Classifier: Framework :: Zope2
Classifier: Framework :: Zope3
Classifier: Programming Language :: Python
Classifier: Topic :: Software Development :: Libraries :: Python Modules
